typecheck
tests
