Metadata-Version: 1.0
Name: typecheck
Version: 0.3.0
Summary: A runtime type-checking module for Python
Home-page: http://www.ilowe.net/software/typecheck
Author: Collin Winter, Iain Lowe
Author-email: collinw@gmail.com, ilowe@cryogen.com
License: MIT License
Keywords: python decorator type-check typesafe typesafety type typing static
Platform: UNKNOWN
Classifier: Intended Audience :: Developers
Classifier: License :: OSI Approved :: MIT License
Classifier: Natural Language :: English
Classifier: Operating System :: OS Independent
Classifier: Programming Language :: Python
Classifier: Topic :: Software Development :: Libraries :: Python Modules
